image_depot/__init__.py
image_depot/depot_type.py
image_depot/image_depot.py
image_depot/depot/__init__.py
image_depot/depot/ai58.py
image_depot/depot/base.py
image_depot/depot/bo_luo.py
image_depot/depot/cat_box.py
image_depot/depot/depot_config.py
image_depot/depot/dig268608.py
image_depot/depot/error.py
image_depot/depot/github.py
image_depot/depot/hakaimg.py
image_depot/depot/hua_ban.py
image_depot/depot/image23.py
image_depot/depot/img_url.py
image_depot/depot/imgbb.py
image_depot/depot/none_type.py
image_depot/depot/pomf_se.py
image_depot/depot/postimages.py
image_depot/depot/pz_al.py
image_depot/depot/riyugo.py
image_depot/depot/sm_ms.py
image_depot/depot/tucnag.py
image_depot/depot/xywm.py
image_depot-0.12.3.dist-info/licenses/LICENSE
image_depot-0.12.3.dist-info/METADATA
image_depot-0.12.3.dist-info/WHEEL
image_depot-0.12.3.dist-info/top_level.txt
image_depot-0.12.3.dist-info/RECORD
