Metadata-Version: 2.4
Name: image_depot
Version: 0.12.3
Summary: 图床上传工具
Author-email: hujingnb <hujingnb@qq.com>
Project-URL: Homepage, https://github.com/hujingnb/image_depot
Project-URL: Bug Tracker, https://github.com/hujingnb/image_depot/issues
Classifier: Programming Language :: Python :: 3
Classifier: License :: OSI Approved :: MIT License
Classifier: Operating System :: OS Independent
Requires-Python: >=3.7
License-File: LICENSE
Requires-Dist: requests
Requires-Dist: filetype
Dynamic: license-file
